{
  "_fv": 66,
  "_type": "tool",
  "definition": {
    "toolType": "Shield",
    "renderType": 1,
    "blockingRenderType": 1,
    "texture": "void_lens",
    "customModelName": "eye_shield:default",
    "blockingModelName": "eye_shield_block:default",
    "name": "Eye Shield",
    "specialInformation": {
      "fixedValue": [
        "ยง9Paralizes every foe in front of the wielder when blocking an attack"
      ]
    },
    "creativeTabs": [
      {
        "value": "CUSTOM:TheDeepVoid"
      }
    ],
    "efficiency": 4.0,
    "attackSpeed": 1.0,
    "enchantability": 10,
    "damageVsEntity": 4.0,
    "usageCount": 1561,
    "glowCondition": {
      "fixedValue": false
    },
    "repairItems": [
      {
        "value": "CUSTOM:VoidLens"
      },
      {
        "value": "CUSTOM:GrimGem"
      },
      {
        "value": "CUSTOM:Onyx"
      },
      {
        "value": "CUSTOM:DesolateSoil"
      }
    ],
    "immuneToFire": false,
    "blockDropsTier": "STONE",
    "blocksAffected": [],
    "stayInGridWhenCrafting": false,
    "damageOnCrafting": false
  }
}