{
  "_fv": 66,
  "_type": "musicdisc",
  "definition": {
    "name": "Music Disc",
    "rarity": "COMMON",
    "texture": "pitch_black_disc",
    "description": "ยง7DARK FANTASY STUDIO - Pitch black",
    "creativeTabs": [
      {
        "value": "CUSTOM:TheDeepVoid"
      }
    ],
    "specialInformation": {
      "fixedValue": []
    },
    "glowCondition": {
      "fixedValue": false
    },
    "music": {
      "value": "CUSTOM:pitch_black"
    },
    "lengthInTicks": 1780,
    "analogOutput": 8
  }
}